README.md
setup.py
mysql_async/__init__.py
mysql_async/connector/__init__.py
mysql_async/connector/connection.py
mysql_async/connector/cursor.py
mysql_async/connector/custom_types.py
mysql_async/connector/network.py
mysql_async/connector/pooling.py
mysql_async/connector/protocol.py
mysql_async/connector/version.py
mysql_async/connector/locales/__init__.py
mysql_async/connector/locales/eng/__init__.py
mysql_async/connector/locales/eng/client_error.py
mysql_connector_async_dd.egg-info/PKG-INFO
mysql_connector_async_dd.egg-info/SOURCES.txt
mysql_connector_async_dd.egg-info/dependency_links.txt
mysql_connector_async_dd.egg-info/requires.txt
mysql_connector_async_dd.egg-info/top_level.txt