Metadata-Version: 1.0
Name: mysql-connector-async-dd
Version: 2.0.2
Summary: mysql async connection
Home-page: https://github.com/waipbmtd/django-weed
Author: Devin
Author-email: waipbmtd@gmail.com
License: MIT
Platform: UNKNOWN
